Workbook
Name Colaboradores: Colaboradores!$A$2:$A$1048576
Name Serviços: Serviços!$A:$A

Sheet Vendas
A1: Tipo de Serviço | B1: Qtde | C1: Valor pago | D1: Valor subtotal | E1: Desconto | F1: Responsável | G1: Data
A2: Impressão normal | B2: 2 | C2: 2 | D2: =VLOOKUP(A2, Serviços!A:B, 2, FALSE) * B2 -> 4 | E2: =IF(D2 >= C2, D2-C2, 0) -> 2
D3: =VLOOKUP(A3, Serviços!A:B, 2, FALSE) * B3 -> #N/A | E3: =IF(D3 >= C3, D3-C3, 0) -> #N/A
D4: =VLOOKUP(A4, Serviços!A:B, 2, FALSE) * B4 -> #N/A | E4: =IF(D4 >= C4, D4-C4, 0) -> #N/A
D5: =VLOOKUP(A5, Serviços!A:B, 2, FALSE) * B5 -> #N/A | E5: =IF(D5 >= C5, D5-C5, 0) -> #N/A
D6: =VLOOKUP(A6, Serviços!A:B, 2, FALSE) * B6 -> #N/A | E6: =IF(D6 >= C6, D6-C6, 0) -> #N/A
D7: =VLOOKUP(A7, Serviços!A:B, 2, FALSE) * B7 -> #N/A | E7: =IF(D7 >= C7, D7-C7, 0) -> #N/A
D8: =VLOOKUP(A8, Serviços!A:B, 2, FALSE) * B8 -> #N/A | E8: =IF(D8 >= C8, D8-C8, 0) -> #N/A
D9: =VLOOKUP(A9, Serviços!A:B, 2, FALSE) * B9 -> #N/A | E9: =IF(D9 >= C9, D9-C9, 0) -> #N/A
D10: =VLOOKUP(A10, Serviços!A:B, 2, FALSE) * B10 -> #N/A | E10: =IF(D10 >= C10, D10-C10, 0) -> #N/A
D11: =VLOOKUP(A11, Serviços!A:B, 2, FALSE) * B11 -> #N/A | E11: =IF(D11 >= C11, D11-C11, 0) -> #N/A
D12: =VLOOKUP(A12, Serviços!A:B, 2, FALSE) * B12 -> #N/A | E12: =IF(D12 >= C12, D12-C12, 0) -> #N/A
D13: =VLOOKUP(A13, Serviços!A:B, 2, FALSE) * B13 -> #N/A | E13: =IF(D13 >= C13, D13-C13, 0) -> #N/A
D14: =VLOOKUP(A14, Serviços!A:B, 2, FALSE) * B14 -> #N/A | E14: =IF(D14 >= C14, D14-C14, 0) -> #N/A
... D151: =VLOOKUP(A151, Serviços!A:B, 2, FALSE) * B151 -> #N/A | E151: =IF(D151 >= C151, D151-C151, 0) -> #N/A
D152: =VLOOKUP(A152, Serviços!A:B, 2, FALSE) * B152 -> #N/A
D153: =VLOOKUP(A153, Serviços!A:B, 2, FALSE) * B153 -> #N/A
D154: =VLOOKUP(A154, Serviços!A:B, 2, FALSE) * B154 -> #N/A
D155: =VLOOKUP(A155, Serviços!A:B, 2, FALSE) * B155 -> #N/A
D156: =VLOOKUP(A156, Serviços!A:B, 2, FALSE) * B156 -> #N/A
D157: =VLOOKUP(A157, Serviços!A:B, 2, FALSE) * B157 -> #N/A
D158: =VLOOKUP(A158, Serviços!A:B, 2, FALSE) * B158 -> #N/A
D159: =VLOOKUP(A159, Serviços!A:B, 2, FALSE) * B159 -> #N/A
D160: =VLOOKUP(A160, Serviços!A:B, 2, FALSE) * B160 -> #N/A
D161: =VLOOKUP(A161, Serviços!A:B, 2, FALSE) * B161 -> #N/A
D162: =VLOOKUP(A162, Serviços!A:B, 2, FALSE) * B162 -> #N/A
D163: =VLOOKUP(A163, Serviços!A:B, 2, FALSE) * B163 -> #N/A
... D555: =VLOOKUP(A555, Serviços!A:B, 2, FALSE) * B555 -> #N/A

Sheet Colaboradores
A1: Nome
A2: Jessiane
A3: Jaqueline
A4: Gabriel
A5: Genilda

Sheet Serviços
A1: Nome | B1: Preço | C1: Gasto de material
A2: Impressão normal | B2: 2 | C2: 0.5
A3: Foto 10x15 | B3: 2.5 | C3: 0.5
A4: Foto 3x4 (6 unidades) | B4: 6 | C4: 0.5
A5: Topo de Bolo (folha foto grossa) | B5: 8 | C5: 2
A6: Curriculo (simples) | B6: 5 | C6: 0.5
A7: Curriculo (mais de uma folha) | B7: 8 | C7: 0.5
A8: Digitalização (simples) | B8: 7 | C8: 0.5
A9: Documento de compra e venda | B9: 10 | C9: 0.5
A10: Documento de compra e venda com leis | B10: 15 | C10: 1
A11: Criar email | B11: 3 | C11: 0.5
A12: Baixar aplicativos | B12: 5 | C12: 0
A13: Xerox (preto e branco) | B13: 0.3 | C13: 0.15
... A21: Pesquisa escolar (1 impressao) | B21: 5 | C21: 0.5
B22: =SUM(B2:B21) -> 112.3 | C22: =SUM(C2:C21) -> 10.95
